<?xml version="1.0" encoding="UTF-8" standalone="yes"?>
<wrapper>
    <window>
        <height>587.0</height>
        <width>935.0</width>
        <x>366.0</x>
        <y>103.0</y>
    </window>
    <preference>
        <fontFamily>Courier New</fontFamily>
        <fontSize>13.0</fontSize>
        <charset>utf-8</charset>
        <theme>Dark</theme>
    </preference>
    <highLights>
        <markSearchPattern>true</markSearchPattern>
        <highLight>
            <ignoreCase>false</ignoreCase>
            <pattern>ERROR</pattern>
            <foreground>0xcc3333ff</foreground>
            <background>0xffffff00</background>
            <bold>true</bold>
            <italic>false</italic>
            <order>10</order>
        </highLight>
    </highLights>
    <servers>
        <server>
            <name>10.64.33.95 (logs)</name>
            <host>10.64.33.95</host>
            <port>22</port>
            <account>eservice</account>
            <password>eservice</password>
            <expanded>true</expanded>
            <logs>
                <logPath>
                    <path>/wls/eservice/ESFRONT/logs/FRServer1_console.log</path>
                </logPath>
                <logPath>
                    <path>/wls/eservice/wls1036_domain/logs/admin_console.log</path>
                </logPath>
            </logs>
        </server>
        <server>
            <name>giiiiiiiiiiiiiiiiit</name>
            <host>192.168.56.102</host>
            <port>22</port>
            <account>nanashi07</account>
            <password>coriander</password>
            <expanded>true</expanded>
            <logs>
                <logPath>
                    <path>/home/nanashi07/mylog.log</path>
                </logPath>
            </logs>
        </server>
    </servers>
</wrapper>
